[
    {
        "game": "範例遊戲",
        "points": 50,
        "initiator": "房主",
        "avatar": "",
        "roomID": "123456"
    },
    {
        "game": "範例遊戲",
        "points": 50,
        "initiator": "房主",
        "avatar": "",
        "roomID": "123456"
    },
    {
        "game": "範例遊戲",
        "points": 50,
        "initiator": "房主",
        "avatar": "",
        "roomID": "123456"
    },
    {
        "game": "範例遊戲",
        "points": 50,
        "initiator": "房主",
        "avatar": "",
        "roomID": "123456"
    },
    {
        "game": "範例遊戲",
        "points": 50,
        "initiator": "房主",
        "avatar": "",
        "roomID": "123456"
    }
]
